setup.py
abdallah_dsnd_distributions/Binomialdistribution.py
abdallah_dsnd_distributions/Gaussiandistribution.py
abdallah_dsnd_distributions/Generaldistribution.py
abdallah_dsnd_distributions/__init__.py
abdallah_dsnd_distributions.egg-info/PKG-INFO
abdallah_dsnd_distributions.egg-info/SOURCES.txt
abdallah_dsnd_distributions.egg-info/dependency_links.txt
abdallah_dsnd_distributions.egg-info/not-zip-safe
abdallah_dsnd_distributions.egg-info/top_level.txt