Metadata-Version: 2.1
Name: abdallah-dsnd-distributions
Version: 0.1
Summary: Gaussian distributions
Author: abdallah
Author-email: abdallah.badarne7@gmail.com
